changyou/__init__.py
changyou/blackbox.html
changyou/changyou.py
changyou/exception.py
changyou/model.py
changyou/tfd.html
changyou/tongdun.py
changyou/utils/__init__.py
changyou/utils/helper.py
changyou-1.1.0.dist-info/LICENSE
changyou-1.1.0.dist-info/METADATA
changyou-1.1.0.dist-info/WHEEL
changyou-1.1.0.dist-info/top_level.txt
changyou-1.1.0.dist-info/RECORD
